electricity_outage_checker/__init__.py
electricity_outage_checker/cli.py
electricity_outage_checker/client.py
electricity_outage_checker/config.py
electricity_outage_checker/models.py
electricity_outage_checker/py.typed
electricity_outage_checker-1.0.2.dist-info/METADATA
electricity_outage_checker-1.0.2.dist-info/WHEEL
electricity_outage_checker-1.0.2.dist-info/entry_points.txt
electricity_outage_checker-1.0.2.dist-info/licenses/LICENSE
electricity_outage_checker-1.0.2.dist-info/RECORD
